<annotation>
	<folder>screens</folder>
	<filename>Screenshot_9.png</filename>
	<path>C:\Users\mailt\github\7dtd-tools\screens\Screenshot_9.png</path>
	<source>
		<database>Unknown</database>
	</source>
	<size>
		<width>2559</width>
		<height>1439</height>
		<depth>3</depth>
	</size>
	<segmented>0</segmented>
	<object>
		<name>tree</name>
		<pose>Unspecified</pose>
		<truncated>0</truncated>
		<difficult>0</difficult>
		<bndbox>
			<xmin>91</xmin>
			<ymin>302</ymin>
			<xmax>360</xmax>
			<ymax>945</ymax>
		</bndbox>
	</object>
	<object>
		<name>tree</name>
		<pose>Unspecified</pose>
		<truncated>0</truncated>
		<difficult>0</difficult>
		<bndbox>
			<xmin>11</xmin>
			<ymin>391</ymin>
			<xmax>94</xmax>
			<ymax>535</ymax>
		</bndbox>
	</object>
	<object>
		<name>tree</name>
		<pose>Unspecified</pose>
		<truncated>0</truncated>
		<difficult>0</difficult>
		<bndbox>
			<xmin>420</xmin>
			<ymin>476</ymin>
			<xmax>495</xmax>
			<ymax>589</ymax>
		</bndbox>
	</object>
	<object>
		<name>tree</name>
		<pose>Unspecified</pose>
		<truncated>0</truncated>
		<difficult>0</difficult>
		<bndbox>
			<xmin>725</xmin>
			<ymin>190</ymin>
			<xmax>929</xmax>
			<ymax>1012</ymax>
		</bndbox>
	</object>
	<object>
		<name>tree</name>
		<pose>Unspecified</pose>
		<truncated>0</truncated>
		<difficult>0</difficult>
		<bndbox>
			<xmin>1029</xmin>
			<ymin>556</ymin>
			<xmax>1103</xmax>
			<ymax>765</ymax>
		</bndbox>
	</object>
	<object>
		<name>tree</name>
		<pose>Unspecified</pose>
		<truncated>0</truncated>
		<difficult>0</difficult>
		<bndbox>
			<xmin>1296</xmin>
			<ymin>186</ymin>
			<xmax>2148</xmax>
			<ymax>1092</ymax>
		</bndbox>
	</object>
	<object>
		<name>tree</name>
		<pose>Unspecified</pose>
		<truncated>0</truncated>
		<difficult>0</difficult>
		<bndbox>
			<xmin>2072</xmin>
			<ymin>237</ymin>
			<xmax>2295</xmax>
			<ymax>903</ymax>
		</bndbox>
	</object>
	<object>
		<name>tree</name>
		<pose>Unspecified</pose>
		<truncated>1</truncated>
		<difficult>0</difficult>
		<bndbox>
			<xmin>2061</xmin>
			<ymin>1</ymin>
			<xmax>2336</xmax>
			<ymax>819</ymax>
		</bndbox>
	</object>
	<object>
		<name>tree</name>
		<pose>Unspecified</pose>
		<truncated>0</truncated>
		<difficult>0</difficult>
		<bndbox>
			<xmin>2343</xmin>
			<ymin>245</ymin>
			<xmax>2556</xmax>
			<ymax>796</ymax>
		</bndbox>
	</object>
	<object>
		<name>zombie</name>
		<pose>Unspecified</pose>
		<truncated>0</truncated>
		<difficult>0</difficult>
		<bndbox>
			<xmin>909</xmin>
			<ymin>912</ymin>
			<xmax>969</xmax>
			<ymax>979</ymax>
		</bndbox>
	</object>
	<object>
		<name>zombie</name>
		<pose>Unspecified</pose>
		<truncated>0</truncated>
		<difficult>0</difficult>
		<bndbox>
			<xmin>1077</xmin>
			<ymin>924</ymin>
			<xmax>1117</xmax>
			<ymax>1025</ymax>
		</bndbox>
	</object>
</annotation>
